tests/__init__.py
tests/test_config.py
tinvest_robot_perevalov/__init__.py
tinvest_robot_perevalov/_config.py
tinvest_robot_perevalov/_db.py
tinvest_robot_perevalov/news_fetcher.py
tinvest_robot_perevalov/sentiment_analyzer.py
tinvest_robot_perevalov/trader.py
tinvest_robot_perevalov-0.1.3.dist-info/METADATA
tinvest_robot_perevalov-0.1.3.dist-info/WHEEL
tinvest_robot_perevalov-0.1.3.dist-info/top_level.txt
tinvest_robot_perevalov-0.1.3.dist-info/RECORD
