Metadata-Version: 2.1
Name: tinvest-robot-perevalov
Version: 0.1.3
Summary: A package that implements a news sentiment based strategy for trading using Tiknoff Invest API
Home-page: https://github.com/Perevalov/tinvest_robot
Author: Aleksandr Perevalov
Author-email: perevalovproduction@gmail.com
License: UNKNOWN
Platform: UNKNOWN
Classifier: Programming Language :: Python
Classifier: Programming Language :: Python :: 3
Classifier: Programming Language :: Python :: 3.6
Classifier: Programming Language :: Python :: 3.7
Classifier: Programming Language :: Python :: 3.8
Classifier: License :: OSI Approved :: MIT License
Classifier: Operating System :: OS Independent
Requires-Python: >=3.6
Requires-Dist: transformers (==4.8.2)
Requires-Dist: pytz (==2019.3)
Requires-Dist: scipy (==1.4.1)
Requires-Dist: APScheduler (==3.6.3)
Requires-Dist: feedparser (==6.0.8)
Requires-Dist: tinkoff
